execubot_py/__init__.py
execubot_py/cli.py
execubot_py/generator.py
execubot_py/solver.py
execubot_py/translation.py
execubot_py-2.4.dist-info/licenses/COPYING
execubot_py-2.4.dist-info/WHEEL
execubot_py-2.4.dist-info/entry_points.txt
execubot_py-2.4.dist-info/METADATA
execubot_py-2.4.dist-info/RECORD
