Metadata-Version: 2.4
Name: execubot-py
Version: 2.4
Summary: Package providing the Execubot project Python code (https://execubot.fr).
Author: Florent Gallaire, Célia Piquet
Author-email: Florent Gallaire <fgallaire@gmail.com>, Célia Piquet <cepiquet@proton.me>
License-Expression: GPL-3.0-or-later
License-File: COPYING
Classifier: Development Status :: 5 - Production/Stable
Classifier: Intended Audience :: Education
Classifier: Environment :: Console
Classifier: Environment :: Web Environment
Classifier: License :: OSI Approved :: GNU General Public License v3 or later (GPLv3+)
Classifier: Topic :: Games/Entertainment
Classifier: Programming Language :: Python
Classifier: Programming Language :: Python :: 3
Classifier: Programming Language :: Python :: 3.10
Classifier: Programming Language :: Python :: 3.11
Classifier: Programming Language :: Python :: 3.12
Classifier: Programming Language :: Python :: 3.13
Classifier: Programming Language :: Python :: 3.14
Classifier: Programming Language :: Python :: 3.15
Classifier: Programming Language :: Python :: Implementation :: CPython
Requires-Dist: docopt>=0.6.2
Requires-Dist: natsort>=8.4.0
Requires-Python: >=3.10
Project-URL: Documentation, https://execubot.forge.apps.education.fr
Project-URL: Homepage, https://execubot.fr
Project-URL: Issues, https://forge.apps.education.fr/cpiquet/execubot/issues
Project-URL: Repository, https://forge.apps.education.fr/cpiquet/execubot
